[
  {
    "chlink": "https://butsoccer.xyz/hizenstv/player/chs/animetv.html",
    "chsite": "nosite",
    "chcategory": "Entretenimento",
    "chsocial": "nosocial",
    "chyoutube": "https://www.youtube.com/",
    "chname": "Hizens Anime",
    "chimg": "https://raw.githubusercontent.com/ButterflyAquariumStudios/hizenstv/main/img/HizensAnime.png",
    "chid": "120",
    "chdesc": "Transmissão original da AnimeTV. Transmissão IPTV.",
    "chprogram": "https://raw.githubusercontent.com/ButterflyAquariumStudios/hizenstv/main/epg.json"
  },
  {
    "chlink": "https://player.twitch.tv/?channel=Chel_channel&parent=hizentv",
    "chsite": "https://www.twitch.tv/chel_channel",
    "chcategory": "Entretenimento",
    "chsocial": "nosocial",
    "chyoutube": "https://www.youtube.com/",
    "chname": "Chel Channel",
    "chimg": "https://raw.githubusercontent.com/ButterflyAquariumStudios/hizenstv/main/img/ChelChannel.png",
    "chid": "150",
    "chdesc": "Transmitido direto do Twitch.",
    "chprogram": "https://raw.githubusercontent.com/ButterflyAquariumStudios/hizenstv/main/epg.json"
  },
  {
    "chlink": "https://player.twitch.tv/?channel=shel_channel&parent=hizenstv",
    "chsite": "https://www.twitch.tv/shel_channel",
    "chcategory": "Entretenimento",
    "chsocial": "nosocial",
    "chyoutube": "https://www.youtube.com/",
    "chname": "Shel Channel",
    "chimg": "https://raw.githubusercontent.com/ButterflyAquariumStudios/hizenstv/main/img/ChelChannel.png",
    "chid": "151",
    "chdesc": "Transmitido direto do Twitch.",
    "chprogram": "https://raw.githubusercontent.com/ButterflyAquariumStudios/hizenstv/main/epg.json"
  },
  {
    "chlink": "https://butsoccer.xyz/hizenstv/player/chs/vmtv.html",
    "chsite": "nosite",
    "chcategory": "Entretenimento",
    "chsocial": "nosocial",
    "chyoutube": "https://www.youtube.com/",
    "chname": "VMTV",
    "chimg": "https://raw.githubusercontent.com/ButterflyAquariumStudios/hizenstv/main/img/VM.png",
    "chid": "152",
    "chdesc": "Transmissão IPTV.",
    "chprogram": "https://raw.githubusercontent.com/ButterflyAquariumStudios/hizenstv/main/epg.json"
  },
  {
    "chlink": "https://booyah.live/standalone/liveplayer/34850987?room_id=34659740",
    "chsite": "https://www.youtube.com",
    "chcategory": "Entretenimento",
    "chsocial": "nosocial",
    "chyoutube": "https://www.youtube.com/",
    "chname": "Loading TV",
    "chimg": "https://raw.githubusercontent.com/ButterflyAquariumStudios/hizenstv/main/img/LoadingTV.png",
    "chid": "153",
    "chdesc": "Transmissão IPTV.",
    "chprogram": "https://raw.githubusercontent.com/ButterflyAquariumStudios/hizenstv/main/epg.json"
  },
  {
    "chlink": "https://playerv.zcast.com.br/video/yeeaah/1/true/false/YzNKMk15NTZZMkZ6ZEM1amIyMHVZbkk9K1o=/16:9/nocover/nao/",
    "chsite": "https://www.youtube.com",
    "chcategory": "Entretenimento",
    "chsocial": "nosocial",
    "chyoutube": "https://www.youtube.com/",
    "chname": "Yeeaah",
    "chimg": "https://raw.githubusercontent.com/ButterflyAquariumStudios/hizenstv/main/img/Yeeaah.png",
    "chid": "154",
    "chdesc": "Transmissão oficial do site Yeeaah.",
    "chprogram": "https://raw.githubusercontent.com/ButterflyAquariumStudios/hizenstv/main/epg.json"
  },
  {
    "chlink": "https://player.twitch.tv/?channel=SBTGamesOficial&parent=hizentv",
    "chsite": "https://www.youtube.com",
    "chcategory": "Entretenimento",
    "chsocial": "nosocial",
    "chyoutube": "https://www.youtube.com/",
    "chname": "SBT Games",
    "chimg": "https://raw.githubusercontent.com/ButterflyAquariumStudios/hizenstv/main/img/SBTGames.png",
    "chid": "155",
    "chdesc": "Transmitido direto da Twitch.",
    "chprogram": "https://raw.githubusercontent.com/ButterflyAquariumStudios/hizenstv/main/epg.json"
  },
  {
    "chlink": "https://butsoccer.xyz/hizenstv/player/chs/player.php?ch=https://stmv1.srvstm.com/tvserie/tvserie/playlist.m3u8",
    "chsite": "https://www.youtube.com",
    "chcategory": "Entretenimento",
    "chsocial": "nosocial",
    "chyoutube": "https://www.youtube.com/",
    "chname": "As Panteras",
    "chimg": "https://raw.githubusercontent.com/ButterflyAquariumStudios/hizenstv/main/img/AsPanteras.png",
    "chid": "156",
    "chdesc": "Transmissão IPTV.",
    "chprogram": "https://raw.githubusercontent.com/ButterflyAquariumStudios/hizenstv/main/epg.json"
  },
  {
    "chlink": "https://butsoccer.xyz/hizenstv/player/chs/player.php?ch=https://stmv1.srvstm.com/tvserie2/tvserie2/playlist.m3u8",
    "chsite": "https://www.youtube.com",
    "chcategory": "Entretenimento",
    "chsocial": "nosocial",
    "chyoutube": "https://www.youtube.com/",
    "chname": "A Mulher Biônica",
    "chimg": "https://raw.githubusercontent.com/ButterflyAquariumStudios/hizenstv/main/img/MulherBionica.png",
    "chid": "157",
    "chdesc": "Transmissão IPTV.",
    "chprogram": "https://raw.githubusercontent.com/ButterflyAquariumStudios/hizenstv/main/epg.json"
  },
  {
    "chlink": "https://butsoccer.xyz/hizenstv/player/chs/player.php?ch=https://StmV1.srvstm.com/tvserie3/tvserie3/playlist.m3u8",
    "chsite": "https://www.youtube.com",
    "chcategory": "Entretenimento",
    "chsocial": "nosocial",
    "chyoutube": "https://www.youtube.com/",
    "chname": "Star Trek - Jornada nas Estrelas",
    "chimg": "https://raw.githubusercontent.com/ButterflyAquariumStudios/hizenstv/main/img/StarTrek.png",
    "chid": "158",
    "chdesc": "Transmissão IPTV.",
    "chprogram": "https://raw.githubusercontent.com/ButterflyAquariumStudios/hizenstv/main/epg.json"
  },
  {
    "chlink": "https://butsoccer.xyz/hizenstv/player/chs/player.php?ch=https://a357e37df8ec46719fdeffa29a3e8e40.mediatailor.us-east-1.amazonaws.com/v1/master/44f73ba4d03e9607dcd9bebdcb8494d86964f1d8/Plex-intl_PeopleAreAwesome/playlist.m3u8",
    "chsite": "https://www.youtube.com",
    "chcategory": "Entretenimento",
    "chsocial": "nosocial",
    "chyoutube": "https://www.youtube.com/",
    "chname": "People are Awesome",
    "chimg": "https://raw.githubusercontent.com/ButterflyAquariumStudios/hizenstv/main/img/PeopleAreAwesome.png",
    "chid": "159",
    "chdesc": "Transmissão IPTV (PlexTV).",
    "chprogram": "https://raw.githubusercontent.com/ButterflyAquariumStudios/hizenstv/main/epg.json"
  },
  {
    "chlink": "https://butsoccer.xyz/hizenstv/player/chs/player.php?ch=https://04799df414944908856c6c521891945f.mediatailor.us-east-1.amazonaws.com/v1/master/44f73ba4d03e9607dcd9bebdcb8494d86964f1d8/Plex-intl_WeatherSpy/playlist.m3u8",
    "chsite": "https://www.youtube.com",
    "chcategory": "Entretenimento",
    "chsocial": "nosocial",
    "chyoutube": "https://www.youtube.com/",
    "chname": "WeatherSpy",
    "chimg": "https://raw.githubusercontent.com/ButterflyAquariumStudios/hizenstv/main/img/WeatherSpy.png",
    "chid": "160",
    "chdesc": "Transmissão IPTV (PlexTV).",
    "chprogram": "https://raw.githubusercontent.com/ButterflyAquariumStudios/hizenstv/main/epg.json"
  },
  {
    "chlink": "https://butsoccer.xyz/hizenstv/player/chs/player.php?ch=https://stmv1.srvif.com/manchetebahia/manchetebahia/playlist.m3u8",
    "chsite": "https://www.youtube.com",
    "chcategory": "Entretenimento",
    "chsocial": "nosocial",
    "chyoutube": "https://www.youtube.com/",
    "chname": "TV Manchete Bahia",
    "chimg": "https://raw.githubusercontent.com/ButterflyAquariumStudios/hizenstv/main/img/TVMancheteBahia.png",
    "chid": "161",
    "chdesc": "Transmissão IPTV.",
    "chprogram": "https://raw.githubusercontent.com/ButterflyAquariumStudios/hizenstv/main/epg.json"
  },
  {
    "chlink": "https://www.youtube.com/embed/playlist?list=PLBv9h8SYk1vwJwdxxT6TsL3vDyLJklo3Z&index=RANDOMIZELOL&autostart=1&repeat=1",
    "chsite": "https://www.youtube.com",
    "chcategory": "Entretenimento",
    "chsocial": "nosocial",
    "chyoutube": "https://www.youtube.com/",
    "chname": "MrPoladoful Adventures",
    "chimg": "https://raw.githubusercontent.com/ButterflyAquariumStudios/hizenstv/main/img/MrPoladofulOD.png",
    "chid": "162",
    "chdesc": "Playlist transmitida direto do YouTube.",
    "chprogram": "https://raw.githubusercontent.com/ButterflyAquariumStudios/hizenstv/main/epg.json"
  },
  {
    "chlink": "https://player.twitch.tv/?channel=2HomenseMeio&parent=hizenstv",
    "chsite": "https://www.youtube.com",
    "chcategory": "Entretenimento",
    "chsocial": "nosocial",
    "chyoutube": "https://www.youtube.com/",
    "chname": "Dois Homens e Meio",
    "chimg": "https://raw.githubusercontent.com/ButterflyAquariumStudios/hizenstv/main/img/DoisHomenseMeio.png",
    "chid": "163",
    "chdesc": "Transmitido direto da Twitch.",
    "chprogram": "https://raw.githubusercontent.com/ButterflyAquariumStudios/hizenstv/main/epg.json"
  }
]